BioExt/__init__.py
BioExt/align/__init__.py
BioExt/align/_align.cpython-35m-darwin.so
BioExt/args/__init__.py
BioExt/collections/__init__.py
BioExt/collections/_counter.py
BioExt/collections/_ordereddict.py
BioExt/data/fonts/ttf/Roboto-Black.ttf
BioExt/data/fonts/ttf/Roboto-BlackItalic.ttf
BioExt/data/fonts/ttf/Roboto-Bold.ttf
BioExt/data/fonts/ttf/Roboto-BoldCondensed.ttf
BioExt/data/fonts/ttf/Roboto-BoldCondensedItalic.ttf
BioExt/data/fonts/ttf/Roboto-BoldItalic.ttf
BioExt/data/fonts/ttf/Roboto-Condensed.ttf
BioExt/data/fonts/ttf/Roboto-CondensedItalic.ttf
BioExt/data/fonts/ttf/Roboto-Italic.ttf
BioExt/data/fonts/ttf/Roboto-Light.ttf
BioExt/data/fonts/ttf/Roboto-LightItalic.ttf
BioExt/data/fonts/ttf/Roboto-Medium.ttf
BioExt/data/fonts/ttf/Roboto-MediumItalic.ttf
BioExt/data/fonts/ttf/Roboto-Regular.ttf
BioExt/data/fonts/ttf/Roboto-Thin.ttf
BioExt/data/fonts/ttf/Roboto-ThinItalic.ttf
BioExt/data/references/hxb2/HXB2_env.gb
BioExt/data/references/hxb2/HXB2_gag.fa
BioExt/data/references/hxb2/HXB2_int.fa
BioExt/data/references/hxb2/HXB2_nef.fa
BioExt/data/references/hxb2/HXB2_pol.fa
BioExt/data/references/hxb2/HXB2_pr.fa
BioExt/data/references/hxb2/HXB2_prrt.fa
BioExt/data/references/hxb2/HXB2_rev.fa
BioExt/data/references/hxb2/HXB2_rt.fa
BioExt/data/references/hxb2/HXB2_tat.fa
BioExt/data/references/hxb2/HXB2_vif.fa
BioExt/data/references/hxb2/HXB2_vpr.fa
BioExt/data/references/hxb2/HXB2_vpu.fa
BioExt/data/references/nl4-3/NL4_3_env.fna
BioExt/data/references/nl4-3/NL4_3_gag.fna
BioExt/data/references/nl4-3/NL4_3_nef.fna
BioExt/data/references/nl4-3/NL4_3_pol.fna
BioExt/data/references/nl4-3/NL4_3_prrt.fna
BioExt/data/references/nl4-3/NL4_3_rev.fna
BioExt/data/references/nl4-3/NL4_3_tat.fna
BioExt/data/references/nl4-3/NL4_3_vif.fna
BioExt/data/references/nl4-3/NL4_3_vpr.fna
BioExt/data/references/nl4-3/NL4_3_vpu.fna
BioExt/data/scorematrices/BLOSUM62.txt
BioExt/data/scorematrices/HIV_BETWEEN_F.txt
biopython_extensions-0.18.0.dist-info/DESCRIPTION.rst
biopython_extensions-0.18.0.dist-info/METADATA
biopython_extensions-0.18.0.dist-info/RECORD
biopython_extensions-0.18.0.dist-info/WHEEL
biopython_extensions-0.18.0.dist-info/metadata.json
biopython_extensions-0.18.0.dist-info/top_level.txt
