Metadata-Version: 2.0
Name: biopython-extensions
Version: 0.18.0
Summary: Misc utilities and definitions not included or hidden in BioPython
Home-page: http://github.com/veg/bioext
Author: N Lance Hepler
Author-email: nlhepler@gmail.com
License: GNU GPL version 3
Platform: UNKNOWN
Requires-Dist: biopython (>=1.58)
Requires-Dist: numpy (>=1.6)
Requires-Dist: pysam (<0.9,>=0.7.5)
Requires-Dist: scipy (>=0.15)
Requires-Dist: six
